{
  "schemaVersion": 1,
  "id": "${mod_id}",
  "version": "${version}",

  "name": "${mod_name}",
  "description": "Template mod",
  "authors": [
    {
      "name": "GiantNuker",
      "contact": {
        "homepage": "https://giantnuker.github.io",
        "sources": "https://github.com/GiantNuker",
        "email": "indigoa.coding@gmail.com"
      }
    }
  ],
  "contact": {
    "homepage": "https://giantnuker.github.io",
    "sources": "https://github.com/GiantNuker/<MOD>",
    "issues": "https://github.com/GiantNuker/<MOD>/issues",
    "email": "indigoa.coding@gmail.com"
  },

  "license": "Apache_2.0",
  "icon": "assets/${mod_id}/icon.png",

  "environment": "*",
  "entrypoints": {
    "main": [
      "io.github.giantnuker.guilds.Guilds"
    ]
  },
  "mixins": [
    "mixins.${mod_id}.json"
  ],

  "depends": {
    "fabricloader": ">=0.7.2"
  }
}